mcp_notes_server/__init__.py
mcp_notes_server/server.py
mcp_notes_server-0.1.3.dist-info/licenses/LICENSE
mcp_notes_server-0.1.3.dist-info/METADATA
mcp_notes_server-0.1.3.dist-info/WHEEL
mcp_notes_server-0.1.3.dist-info/top_level.txt
mcp_notes_server-0.1.3.dist-info/RECORD
