Metadata-Version: 2.4
Name: mcp-notes-server
Version: 0.1.3
Summary: A Model Context Protocol server for developer note-taking
Home-page: https://mcp-hunt.com
Author: filib
Author-email: filib <filib@pypi.org>
License: MIT
Project-URL: Homepage, https://mcp-hunt.com
Project-URL: Documentation, https://github.com/dekdee/note-taking-mcp#readme
Project-URL: Repository, https://github.com/dekdee/note-taking-mcp.git
Project-URL: Issues, https://github.com/dekdee/note-taking-mcp/issues
Requires-Python: >=3.8
License-File: LICENSE
Requires-Dist: mcp>=0.1.0
Requires-Dist: pydantic>=2.0.0
Dynamic: author
Dynamic: home-page
Dynamic: license-file
Dynamic: requires-python
